bmi-calculator/__init__.py
bmi-calculator/bmi_calculator.py
bmi_calculator/__init__.py
bmi_calculator/bmi_calculator.py
bmi_kalculator/__init__.py
bmi_kalculator/bmi_kalculator.py
bmi_kalculator-0.1.0.dist-info/METADATA
bmi_kalculator-0.1.0.dist-info/WHEEL
bmi_kalculator-0.1.0.dist-info/top_level.txt
bmi_kalculator-0.1.0.dist-info/RECORD
