Metadata-Version: 2.1
Name: bmi-kalculator
Version: 0.1.0
Summary: Calculates body mas index (BMI) based on a given set of parameters such as weight, height, gender, age and life-style
Home-page: https://github.com/donwany
Author: Theophilus Siameh
Author-email: theodondre@gmail.com
License: LICENSE.txt
Keywords: python,bmi,bmi calculator
Platform: UNKNOWN
Classifier: License :: OSI Approved :: MIT License
Classifier: Programming Language :: Python :: 3
Classifier: Programming Language :: Python :: 3.7
Requires-Dist: click
